{
    "AX": {
        "error": 0.015151930776197685, 
        "filter_outliers_dict": {
            "filter_outliers": false, 
            "iterations": 1, 
            "std_devs": 2
        }, 
        "fit": "average_SEM", 
        "value": -0.12316136608929092
    }, 
    "H1": {
        "error": 0.016378425772148368, 
        "filter_outliers_dict": {
            "filter_outliers": false, 
            "iterations": 1, 
            "std_devs": 2
        }, 
        "fit": "average_SEM", 
        "value": -0.025790938147991205
    }, 
    "H2": {
        "error": 0.014725055299585685, 
        "filter_outliers_dict": {
            "filter_outliers": false, 
            "iterations": 1, 
            "std_devs": 2
        }, 
        "fit": "average_SEM", 
        "value": -0.039200576227172185
    }, 
    "L1": {
        "error": 0.015287864623825876, 
        "filter_outliers_dict": {
            "filter_outliers": false, 
            "iterations": 1, 
            "std_devs": 2
        }, 
        "fit": "average_SEM", 
        "value": 0.10517835708921888
    }
}