{
    "AX": {
        "error": 0.017536981868289725, 
        "filter_outliers_dict": {
            "filter_outliers": false, 
            "iterations": 1, 
            "std_devs": 2
        }, 
        "fit": "average_SEM", 
        "value": -0.10579078881924171
    }, 
    "H1": {
        "error": 0.016584065159991727, 
        "filter_outliers_dict": {
            "filter_outliers": false, 
            "iterations": 1, 
            "std_devs": 2
        }, 
        "fit": "average_SEM", 
        "value": -0.03056538806571174
    }, 
    "H2": {
        "error": 0.015455698799380017, 
        "filter_outliers_dict": {
            "filter_outliers": false, 
            "iterations": 1, 
            "std_devs": 2
        }, 
        "fit": "average_SEM", 
        "value": -0.050411992589314863
    }, 
    "L1": {
        "error": 0.016042775707539893, 
        "filter_outliers_dict": {
            "filter_outliers": false, 
            "iterations": 1, 
            "std_devs": 2
        }, 
        "fit": "average_SEM", 
        "value": 0.059161384447985146
    }
}